halfspace/__init__.py
halfspace/convex_term.py
halfspace/model.py
halfspace/utils.py
halfspace_optimizer-0.1.0.dist-info/LICENSE
halfspace_optimizer-0.1.0.dist-info/METADATA
halfspace_optimizer-0.1.0.dist-info/WHEEL
halfspace_optimizer-0.1.0.dist-info/top_level.txt
halfspace_optimizer-0.1.0.dist-info/RECORD
