Metadata-Version: 2.1
Name: halfspace-optimizer
Version: 0.1.0
Summary: Cutting-plane solver for mixed-integer convex optimization problems
Author-email: Joshua Ivanhoe <joshua.k.ivanhoe@gmail.com>
License: MIT License
Project-URL: Homepage, https://github.com/joshivanhoe/halfspace
Project-URL: Issues, https://github.com/joshivanhoe/halfspace/issues
Classifier: Programming Language :: Python :: 3
Classifier: License :: OSI Approved :: MIT License
Classifier: Operating System :: OS Independent
Requires-Python: <3.12,>=3.9
License-File: LICENSE
Requires-Dist: mip >=1.15.0
Requires-Dist: numpy >=1.25.2
Requires-Dist: pandas >=2.0.3
Requires-Dist: pre-commit >=3.6.0
Requires-Dist: pytest >=7.4.4
Requires-Dist: pytest-cov >=4.1.0
Requires-Dist: tomli >=2.0.1
